simple_pi/__init__.py
simple_pi/pi.py
simple_pi-0.0.1.dist-info/METADATA
simple_pi-0.0.1.dist-info/WHEEL
simple_pi-0.0.1.dist-info/top_level.txt
simple_pi-0.0.1.dist-info/RECORD
