Metadata-Version: 2.1
Name: simple-pi
Version: 0.0.1
Summary: Simple pi package generator
Home-page: https://gitlab.com/dio-ciencia-de-dados/simple-pi
Author: Diego Soek
License: UNKNOWN
Platform: UNKNOWN
Requires-Python: >=3.5
Requires-Dist: sympy
